elemento_cart/__init__.py
elemento_cart/client.py
elemento_cart/types.py
elemento_cart-1.0.5.dist-info/licenses/LICENSE
elemento_cart-1.0.5.dist-info/METADATA
elemento_cart-1.0.5.dist-info/WHEEL
elemento_cart-1.0.5.dist-info/top_level.txt
elemento_cart-1.0.5.dist-info/RECORD
