Metadata-Version: 2.4
Name: elemento-cart
Version: 1.0.5
Summary: Cart service
Requires-Python: >=3.11
License-File: LICENSE
Requires-Dist: kaiju-tools<3,>=2.4.16
Provides-Extra: server
Requires-Dist: kaiju-redis<3,>=2.4; extra == "server"
Provides-Extra: dev
Requires-Dist: kaiju-tools[dev]; extra == "dev"
Dynamic: license-file
